cascade/core.cpython-39-x86_64-linux-gnu.so
cascade/test.py
cascade/__init__.py
cascade/_version.py
cascade/dynamics/__init__.py
cascade/dynamics/_mascon_asteroid.py
cascade/dynamics/_simple_earth.py
esa_cascade-0.1.7.dist-info/top_level.txt
esa_cascade-0.1.7.dist-info/WHEEL
esa_cascade-0.1.7.dist-info/RECORD
esa_cascade-0.1.7.dist-info/METADATA
esa_cascade.libs/libsleef-f647372d.so.3.5.1
esa_cascade.libs/libgmp-46794942.so.10.4.1
esa_cascade.libs/libfmt-eb4bb319.so.9.1.0
esa_cascade.libs/libtbb-330f1dc8.so.12.7
esa_cascade.libs/libspdlog-b254dfb2.so.1.11.0
esa_cascade.libs/libcascade-3e45f624.so.2.0
esa_cascade.libs/libheyoka-a9639c21.so.24.0
esa_cascade.libs/libmp++-ee020411.so.14.0
esa_cascade.libs/libmpfr-e66c8945.so.6.1.0
esa_cascade.libs/libboost_serialization-1464d039.so.1.80.0
