Metadata-Version: 2.1
Name: esa-cascade
Version: 0.1.7
Summary: N-body simulation for the evolution of orbital environments
Home-page: https://github.com/esa/cascade
Author: Francesco Biscani, Dario Izzo
Author-email: bluescarni@gmail.com
License: MPL-2.0
Keywords: science math physics ode
Platform: Unix
Classifier: Development Status :: 5 - Production/Stable
Classifier: Operating System :: OS Independent
Classifier: Intended Audience :: Science/Research
Classifier: Topic :: Scientific/Engineering
Classifier: Topic :: Scientific/Engineering :: Mathematics
Classifier: Topic :: Scientific/Engineering :: Physics
Classifier: License :: OSI Approved :: Mozilla Public License 2.0 (MPL 2.0)
Classifier: Programming Language :: Python :: 3
Requires-Dist: heyoka (==3.0.*)
Requires-Dist: numpy
